backgammon/__init__.py
backgammon/__main__.py
backgammon/backgammon.py
backgammon/match.py
backgammon/position.py
tests/__init__.py
tests/test_backgammon.py
tests/test_match.py
tests/test_position.py
backgammon-1.2.0.dist-info/LICENSE
backgammon-1.2.0.dist-info/METADATA
backgammon-1.2.0.dist-info/WHEEL
backgammon-1.2.0.dist-info/top_level.txt
backgammon-1.2.0.dist-info/RECORD
