Metadata-Version: 2.1
Name: backgammon
Version: 1.2.0
Summary: Backgammon engine for the Backgammon Network.
Home-page: https://github.com/softwerks/backgammon
Author: Softwerks
Author-email: info@softwerks.com
Classifier: Programming Language :: Python :: 3
Classifier: License :: OSI Approved :: Apache Software License
Classifier: Operating System :: OS Independent
Requires-Python: >=3.7
License-File: LICENSE
